<?xml version = '1.0' encoding = 'UTF-8'?>
<Relation class="oracle.dbtools.crest.model.design.logical.Relation" name="Relation_146" directorySegmentName="seg_0" id="66A858DB-CDD0-72B6-CF8B-E2A0856E1632">
<createdBy>gzerak</createdBy>
<createdTime>2018-01-23 21:42:23 UTC</createdTime>
<ownerDesignName>Polytec_Datenmodel_v1</ownerDesignName>
<identifying>false</identifying>
<optionalSource>true</optionalSource>
<optionalTarget>false</optionalTarget>
<sourceCardinality>1</sourceCardinality>
<sourceEntity>BCE87146-D19D-B0C4-FB5C-11DF2C9C9803</sourceEntity>
<targetCardinalityString>*</targetCardinalityString>
<targetEntity>1D348669-93A3-CA0F-0428-BADEACD0ECA1</targetEntity>
<transferable>true</transferable>
<deleteRule>NO ACTION</deleteRule>
</Relation>